{
  "type": "uk.nhs.notify.ordering.order.read",
  "source": "/ordering/order-read",
  "dataschema": "https://raw.githubusercontent.com/NHSDigital/nhs-notify-standards/refs/heads/main/cloudevents/example-data.json",
  "data": {
    "nhsNumber": "294290-0703",
    "metadata": {
      "teamResponsible": "Team 1",
      "notifyDomain": "Reporting",
      "version": "0.0.8400911940+ZWLg.1.Oz.Kiqq.eDk.PisobrX.xNXdx4IWnRB.l.khBpgr.q1RBSjp.QY2RkzZ6"
    }
  },
  "specversion": "1.0",
  "id": "d8385450-420f-0553-00f0-c98aba97ca1d",
  "subject": "quis elit in",
  "time": "1908-09-21T11:55:49.0Z",
  "datacontenttype": "velit",
  "data_base64": "consectetur dolore tempor aliquip",
  "traceparent": "00-524a78b76a8c5a21ad7d0bcc52e57757-649cf5136fc7c0de-b5",
  "tracestate": "in dolore",
  "partitionkey": "ut",
  "recordedtime": "1898-07-05T14:39:54.0Z",
  "sampledrate": 65169089,
  "sequence": "incididunt",
  "severitytext": "WARN",
  "severitynumber": 6,
  "dataclassification": "internal",
  "dataregulation": "PCI-DSS",
  "datacategory": "sensitive"
}