{
  "type": "uk.nhs.notify.ordering.order.read",
  "source": "/ordering/order-read",
  "data": {
    "nhsNumber": "1084346505",
    "metadata": {
      "teamResponsible": "Team 2",
      "notifyDomain": "Reporting",
      "version": "82710403019.0.0+U-GrDZt0.TyYirxPDcEe.7nZA4vWr.Y.pH.K.8WV4"
    }
  },
  "specversion": "1.0",
  "id": "30fffb76-9d17-208d-dfe3-746dc7882cb1",
  "time": "1910-07-05T09:18:16.0Z",
  "traceparent": "00-bb03982ac3675cb9b0de8fb88a52f858-e974334a8468cf49-ff",
  "partitionkey": "fugiat quis laboris",
  "recordedtime": "1909-01-25T12:01:52.0Z",
  "severitynumber": 5,
  "datacategory": "standard"
}